{"L1": [{"type": "CONFERENCE SYSTEM", "qty": 7}, {"type": "COOLING TOWER", "qty": 3}, {"type": "DB", "qty": 18}, {"type": "EL", "qty": 6}, {"type": "EXIT SIGN", "qty": 6}, {"type": "FCU (CHW)", "qty": 2}, {"type": "FCU (VRF)", "qty": 22}, {"type": "FIRE EXTINGUISHER ABC", "qty": 24}, {"type": "FIRE EXTINGUISHER CO2", "qty": 8}, {"type": "FIREMAN SWITCH", "qty": 3}, {"type": "HAND DRYER", "qty": 2}, {"type": "LPG SYSTEM", "qty": 1}, {"type": "LUMINARIES", "qty": 6}, {"type": "NON CHEMICAL WATER TREATMENT(P5A)", "qty": 2}, {"type": "PANIC BUTTON", "qty": 1}, {"type": "REFRIGERANT LEAK DETECTOR", "qty": 3}, {"type": "S/S/O", "qty": 6}, {"type": "SOUND REINFORCEMENT SYSTEM", "qty": 7}, {"type": "SSB", "qty": 5}, {"type": "VISUAL PROJECTION", "qty": 9}, {"type": "VRF OUTDOOR UNIT", "qty": 2}], "L2": [{"type": "BOOM GATE", "qty": 2}, {"type": "CONFERENCE SYSTEM", "qty": 3}, {"type": "DB", "qty": 18}, {"type": "EL", "qty": 3}, {"type": "EXHAUST FAN", "qty": 1}, {"type": "EXIT SIGN", "qty": 3}, {"type": "FCU (CHW)", "qty": 2}, {"type": "FCU (VRF)", "qty": 21}, {"type": "FIRE EXTINGUISHER ABC", "qty": 13}, {"type": "FIRE EXTINGUISHER CO2", "qty": 6}, {"type": "FIREMAN SWITCH", "qty": 2}, {"type": "HAND DRYER", "qty": 2}, {"type": "HYDRANT PILLAR", "qty": 1}, {"type": "INTEGRATED CONTROL FOR AUDIO & VISUAL SYSTEM", "qty": 1}, {"type": "LUMINARIES", "qty": 3}, {"type": "PANIC BUTTON", "qty": 1}, {"type": "S/S/O", "qty": 3}, {"type": "SOLAR INVERTER", "qty": 9}, {"type": "SOUND REINFORCEMENT SYSTEM", "qty": 3}, {"type": "SSB", "qty": 5}, {"type": "VISUAL PROJECTION", "qty": 11}, {"type": "VRF OUTDOOR UNIT", "qty": 2}], "L3": [{"type": "ACSU", "qty": 4}, {"type": "AHU", "qty": 2}, {"type": "AIR CURTAIN", "qty": 16}, {"type": "AUDIO VISUAL EQUIPMENT", "qty": 1}, {"type": "BIRFUCATED DUCT KITCHEN FAN EQUIPMENT", "qty": 2}, {"type": "DB", "qty": 16}, {"type": "EL", "qty": 2}, {"type": "ELECTRONIC AIR FLITER", "qty": 2}, {"type": "EXIT SIGN", "qty": 2}, {"type": "FCU (ACSU)", "qty": 4}, {"type": "FCU (CHW)", "qty": 2}, {"type": "FIRE EXTINGUISHER ABC", "qty": 13}, {"type": "FIRE EXTINGUISHER CO2", "qty": 3}, {"type": "FIREMAN SWITCH", "qty": 1}, {"type": "GRID CONNECTED PHOTOVOLTAIC(PV)", "qty": 1}, {"type": "HAND DRYER", "qty": 2}, {"type": "KITCHEN EXHAUST HOOD", "qty": 6}, {"type": "KITCHEN MECHANICAL EXAUST FAN", "qty": 2}, {"type": "LUMINARIES", "qty": 2}, {"type": "OUTDOOR LIGHTING", "qty": 4}, {"type": "PANIC BUTTON", "qty": 1}, {"type": "PRESSURISATION FAN", "qty": 3}, {"type": "ROLLER SHUTTER 03 - KAFE A1", "qty": 1}, {"type": "ROLLER SHUTTER 04 - KAFE A1", "qty": 1}, {"type": "ROLLER SHUTTER 05 - KAFE A2", "qty": 1}, {"type": "ROLLER SHUTTER 06 - KAFE A2", "qty": 1}, {"type": "ROLLER SHUTTER 07 - KAFE A3", "qty": 1}, {"type": "ROLLER SHUTTER 08 - KAFE A3", "qty": 1}, {"type": "ROLLER SHUTTER 09 - KAFE B1", "qty": 1}, {"type": "ROLLER SHUTTER 10 - KAFE B1", "qty": 1}, {"type": "ROLLER SHUTTER 11 - KAFE B2", "qty": 1}, {"type": "ROLLER SHUTTER 12 - KAFE B2", "qty": 1}, {"type": "ROLLER SHUTTER 13 - KAFE B3", "qty": 1}, {"type": "ROLLER SHUTTER 14 - KAFE B3", "qty": 1}, {"type": "S/S/O", "qty": 2}, {"type": "SSB", "qty": 6}, {"type": "VAV", "qty": 10}, {"type": "VISUAL PROJECTION", "qty": 1}, {"type": "VSD", "qty": 2}, {"type": "WATER FILTER", "qty": 1}, {"type": "WET CHEMICAL SYSTEM - KAFETERIA", "qty": 6}], "L4": [{"type": "AHU", "qty": 2}, {"type": "DB", "qty": 10}, {"type": "EL", "qty": 1}, {"type": "ELECTRONIC AIR FLITER", "qty": 2}, {"type": "EXIT SIGN", "qty": 1}, {"type": "FCU (CHW)", "qty": 2}, {"type": "FIRE EXTINGUISHER ABC", "qty": 5}, {"type": "FIRE EXTINGUISHER CO2", "qty": 3}, {"type": "FIREMAN SWITCH", "qty": 1}, {"type": "HAND DRYER", "qty": 2}, {"type": "LUMINARIES", "qty": 1}, {"type": "PANIC BUTTON", "qty": 1}, {"type": "S/S/O", "qty": 1}, {"type": "SSB", "qty": 6}, {"type": "VAV", "qty": 12}, {"type": "VSD", "qty": 2}], "L5": [{"type": "AHU", "qty": 2}, {"type": "DB", "qty": 10}, {"type": "EL", "qty": 1}, {"type": "ELECTRONIC AIR FLITER", "qty": 2}, {"type": "EXIT SIGN", "qty": 1}, {"type": "FCU (CHW)", "qty": 2}, {"type": "FIRE EXTINGUISHER ABC", "qty": 5}, {"type": "FIRE EXTINGUISHER CO2", "qty": 3}, {"type": "FIREMAN SWITCH", "qty": 1}, {"type": "HAND DRYER", "qty": 2}, {"type": "LUMINARIES", "qty": 1}, {"type": "PANIC BUTTON", "qty": 1}, {"type": "S/S/O", "qty": 1}, {"type": "SSB", "qty": 5}, {"type": "VAV", "qty": 12}, {"type": "VSD", "qty": 2}], "L6": [{"type": "AHU", "qty": 2}, {"type": "DB", "qty": 10}, {"type": "EL", "qty": 1}, {"type": "ELECTRONIC AIR FLITER", "qty": 2}, {"type": "EXIT SIGN", "qty": 1}, {"type": "FCU (CHW)", "qty": 2}, {"type": "FIRE EXTINGUISHER ABC", "qty": 5}, {"type": "FIRE EXTINGUISHER CO2", "qty": 3}, {"type": "FIREMAN SWITCH", "qty": 1}, {"type": "HAND DRYER", "qty": 2}, {"type": "LUMINARIES", "qty": 1}, {"type": "PANIC BUTTON", "qty": 1}, {"type": "S/S/O", "qty": 1}, {"type": "SSB", "qty": 5}, {"type": "VAV", "qty": 12}, {"type": "VSD", "qty": 2}], "L7": [{"type": "AHU", "qty": 2}, {"type": "DB", "qty": 10}, {"type": "EL", "qty": 1}, {"type": "ELECTRONIC AIR FLITER", "qty": 2}, {"type": "EXIT SIGN", "qty": 1}, {"type": "FCU (CHW)", "qty": 2}, {"type": "FIRE EXTINGUISHER ABC", "qty": 5}, {"type": "FIRE EXTINGUISHER CO2", "qty": 3}, {"type": "FIREMAN SWITCH", "qty": 1}, {"type": "HAND DRYER", "qty": 2}, {"type": "LUMINARIES", "qty": 1}, {"type": "PANIC BUTTON", "qty": 1}, {"type": "S/S/O", "qty": 1}, {"type": "SSB", "qty": 5}, {"type": "VAV", "qty": 12}, {"type": "VSD", "qty": 2}], "L8": [{"type": "AHU", "qty": 2}, {"type": "DB", "qty": 10}, {"type": "EL", "qty": 1}, {"type": "ELECTRONIC AIR FLITER", "qty": 2}, {"type": "EXIT SIGN", "qty": 1}, {"type": "FCU (CHW)", "qty": 2}, {"type": "FIRE EXTINGUISHER ABC", "qty": 5}, {"type": "FIRE EXTINGUISHER CO2", "qty": 3}, {"type": "FIREMAN SWITCH", "qty": 1}, {"type": "HAND DRYER", "qty": 2}, {"type": "LUMINARIES", "qty": 1}, {"type": "PANIC BUTTON", "qty": 1}, {"type": "S/S/O", "qty": 1}, {"type": "SSB", "qty": 5}, {"type": "VAV", "qty": 12}, {"type": "VSD", "qty": 2}], "L9": [{"type": "AHU", "qty": 2}, {"type": "DB", "qty": 10}, {"type": "EL", "qty": 1}, {"type": "ELECTRONIC AIR FLITER", "qty": 2}, {"type": "EXIT SIGN", "qty": 1}, {"type": "FCU (CHW)", "qty": 2}, {"type": "FIRE EXTINGUISHER ABC", "qty": 5}, {"type": "FIRE EXTINGUISHER CO2", "qty": 3}, {"type": "FIREMAN SWITCH", "qty": 1}, {"type": "HAND DRYER", "qty": 2}, {"type": "LUMINARIES", "qty": 1}, {"type": "PANIC BUTTON", "qty": 1}, {"type": "S/S/O", "qty": 1}, {"type": "SSB", "qty": 5}, {"type": "VAV", "qty": 12}, {"type": "VSD", "qty": 2}], "L10": [{"type": "AHU", "qty": 2}, {"type": "DB", "qty": 10}, {"type": "EL", "qty": 1}, {"type": "ELECTRONIC AIR FLITER", "qty": 2}, {"type": "EXIT SIGN", "qty": 1}, {"type": "FCU (CHW)", "qty": 2}, {"type": "FIRE EXTINGUISHER ABC", "qty": 5}, {"type": "FIRE EXTINGUISHER CO2", "qty": 3}, {"type": "FIREMAN SWITCH", "qty": 1}, {"type": "HAND DRYER", "qty": 2}, {"type": "LUMINARIES", "qty": 1}, {"type": "PANIC BUTTON", "qty": 1}, {"type": "S/S/O", "qty": 1}, {"type": "SSB", "qty": 5}, {"type": "VAV", "qty": 12}, {"type": "VSD", "qty": 2}], "L11": [{"type": "AHU", "qty": 2}, {"type": "DB", "qty": 10}, {"type": "EL", "qty": 1}, {"type": "ELECTRONIC AIR FLITER", "qty": 2}, {"type": "EXIT SIGN", "qty": 1}, {"type": "FCU (CHW)", "qty": 2}, {"type": "FIRE EXTINGUISHER ABC", "qty": 5}, {"type": "FIRE EXTINGUISHER CO2", "qty": 3}, {"type": "FIREMAN SWITCH", "qty": 1}, {"type": "HAND DRYER", "qty": 2}, {"type": "LUMINARIES", "qty": 1}, {"type": "PANIC BUTTON", "qty": 1}, {"type": "S/S/O", "qty": 1}, {"type": "SSB", "qty": 5}, {"type": "VAV", "qty": 12}, {"type": "VSD", "qty": 2}], "L12": [{"type": "DB", "qty": 10}, {"type": "EL", "qty": 1}, {"type": "ELECTRONIC AIR FLITER", "qty": 2}, {"type": "EXIT SIGN", "qty": 1}, {"type": "FCU (CHW)", "qty": 2}, {"type": "FIRE EXTINGUISHER ABC", "qty": 5}, {"type": "FIRE EXTINGUISHER CO2", "qty": 3}, {"type": "FIREMAN SWITCH", "qty": 1}, {"type": "HAND DRYER", "qty": 2}, {"type": "LUMINARIES", "qty": 1}, {"type": "PANIC BUTTON", "qty": 1}, {"type": "S/S/O", "qty": 1}, {"type": "SSB", "qty": 5}, {"type": "VAV", "qty": 12}, {"type": "VSD", "qty": 2}], "L13": [{"type": "AHU", "qty": 2}, {"type": "DB", "qty": 10}, {"type": "EL", "qty": 1}, {"type": "ELECTRONIC AIR FLITER", "qty": 2}, {"type": "EXIT SIGN", "qty": 1}, {"type": "FCU (CHW)", "qty": 2}, {"type": "FIRE EXTINGUISHER ABC", "qty": 5}, {"type": "FIRE EXTINGUISHER CO2", "qty": 3}, {"type": "FIREMAN SWITCH", "qty": 1}, {"type": "HAND DRYER", "qty": 2}, {"type": "LUMINARIES", "qty": 1}, {"type": "PANIC BUTTON", "qty": 1}, {"type": "S/S/O", "qty": 1}, {"type": "SSB", "qty": 5}, {"type": "VAV", "qty": 12}, {"type": "VSD", "qty": 2}], "L14": [{"type": "AHU", "qty": 2}, {"type": "DB", "qty": 10}, {"type": "EL", "qty": 1}, {"type": "ELECTRONIC AIR FLITER", "qty": 2}, {"type": "EXIT SIGN", "qty": 1}, {"type": "FCU (CHW)", "qty": 2}, {"type": "FIRE EXTINGUISHER ABC", "qty": 5}, {"type": "FIRE EXTINGUISHER CO2", "qty": 3}, {"type": "FIREMAN SWITCH", "qty": 1}, {"type": "HAND DRYER", "qty": 2}, {"type": "LUMINARIES", "qty": 1}, {"type": "PANIC BUTTON", "qty": 1}, {"type": "S/S/O", "qty": 1}, {"type": "SSB", "qty": 5}, {"type": "VAV", "qty": 12}, {"type": "VSD", "qty": 2}], "L15": [{"type": "AHU", "qty": 2}, {"type": "DB", "qty": 10}, {"type": "EL", "qty": 1}, {"type": "ELECTRONIC AIR FLITER", "qty": 2}, {"type": "EXIT SIGN", "qty": 1}, {"type": "FCU (CHW)", "qty": 2}, {"type": "FIRE EXTINGUISHER ABC", "qty": 5}, {"type": "FIRE EXTINGUISHER CO2", "qty": 3}, {"type": "FIREMAN SWITCH", "qty": 1}, {"type": "HAND DRYER", "qty": 2}, {"type": "LUMINARIES", "qty": 1}, {"type": "PANIC BUTTON", "qty": 1}, {"type": "S/S/O", "qty": 1}, {"type": "SSB", "qty": 5}, {"type": "VAV", "qty": 10}, {"type": "VSD", "qty": 2}], "L16": [{"type": "DB", "qty": 10}, {"type": "EL", "qty": 1}, {"type": "ELECTRONIC AIR FLITER", "qty": 2}, {"type": "EXIT SIGN", "qty": 1}, {"type": "FCU (CHW)", "qty": 2}, {"type": "FIRE EXTINGUISHER ABC", "qty": 5}, {"type": "FIRE EXTINGUISHER CO2", "qty": 3}, {"type": "FIREMAN SWITCH", "qty": 1}, {"type": "HAND DRYER", "qty": 2}, {"type": "LUMINARIES", "qty": 1}, {"type": "PANIC BUTTON", "qty": 1}, {"type": "S/S/O", "qty": 1}, {"type": "SSB", "qty": 5}, {"type": "VAV", "qty": 12}, {"type": "VSD", "qty": 2}], "L17": [{"type": "AHU", "qty": 2}, {"type": "DB", "qty": 10}, {"type": "EL", "qty": 1}, {"type": "ELECTRONIC AIR FLITER", "qty": 2}, {"type": "EXIT SIGN", "qty": 1}, {"type": "FCU (CHW)", "qty": 2}, {"type": "FIRE EXTINGUISHER ABC", "qty": 5}, {"type": "FIRE EXTINGUISHER CO2", "qty": 3}, {"type": "FIREMAN SWITCH", "qty": 1}, {"type": "HAND DRYER", "qty": 2}, {"type": "LUMINARIES", "qty": 1}, {"type": "PANIC BUTTON", "qty": 1}, {"type": "S/S/O", "qty": 1}, {"type": "SSB", "qty": 5}, {"type": "VAV", "qty": 12}, {"type": "VSD", "qty": 2}], "L18": [{"type": "ACB", "qty": 1}, {"type": "ACSU", "qty": 2}, {"type": "CAP BANK", "qty": 2}, {"type": "CHILLED WATER EXPANSION TANK", "qty": 1}, {"type": "COLD WATER INTERMIDIATE SUCTION PUMP", "qty": 1}, {"type": "COOLING TOWER MAKE UP WATER STORAGE TANK", "qty": 1}, {"type": "DB", "qty": 4}, {"type": "DCW INTERMEDIATE STORAGE TANK 1(BASIN)", "qty": 1}, {"type": "DCW INTERMEDIATE STORAGE TANK 2(WC&URINAL)", "qty": 1}, {"type": "DCW INTERMEDIATE SUCTION TANK", "qty": 1}, {"type": "EL", "qty": 1}, {"type": "EXHAUST FAN", "qty": 3}, {"type": "EXIT SIGN", "qty": 1}, {"type": "FAN", "qty": 2}, {"type": "FCU (CHW)", "qty": 1}, {"type": "FIRE EXTINGUISHER ABC", "qty": 7}, {"type": "FIRE EXTINGUISHER CO2", "qty": 5}, {"type": "FIREMAN SWITCH", "qty": 1}, {"type": "FM 200", "qty": 2}, {"type": "FRESH AIR FAN", "qty": 1}, {"type": "HEAT EXCHANGER", "qty": 2}, {"type": "HEAT RECOVERY WHEEL", "qty": 1}, {"type": "LIFT-PL07 LOWZONE", "qty": 1}, {"type": "LIFT-PL08 LOWZONE", "qty": 1}, {"type": "LIFT-PL09 LOWZONE", "qty": 1}, {"type": "LIFT-PL10 LOWZONE", "qty": 1}, {"type": "LIFT-PL11 LOWZONE", "qty": 1}, {"type": "LIFT-PL12 LOWZONE", "qty": 1}, {"type": "LUMINARIES", "qty": 1}, {"type": "LV ROOM", "qty": 1}, {"type": "METERING (VOLT & AMPS)", "qty": 1}, {"type": "MSB", "qty": 2}, {"type": "PRESSURISATION FAN", "qty": 4}, {"type": "RMU", "qty": 1}, {"type": "S/S/O", "qty": 1}, {"type": "SECONDARY CHILLED WATER PUMP (CHWP)", "qty": 3}, {"type": "SMOKE SPILL FAN", "qty": 3}, {"type": "SPRINKLER DUTY PUMP CONTROL PANEL-STAGE3", "qty": 1}, {"type": "SPRINKLER DUTY PUMP CONTROL PANEL-STAGE4", "qty": 1}, {"type": "SPRINKLER DUTY PUMP-STAGE3", "qty": 1}, {"type": "SPRINKLER DUTY PUMP-STAGE4", "qty": 1}, {"type": "SPRINKLER JOCKEY PUMP-STAGE3", "qty": 1}, {"type": "SPRINKLER JOCKEY PUMP-STAGE4", "qty": 1}, {"type": "SPRINKLER STANDBY PUMP-STAGE3", "qty": 1}, {"type": "SPRINKLER STANDBY PUMP-STAGE4", "qty": 1}, {"type": "SPRINKLER TANK", "qty": 1}, {"type": "SSB", "qty": 8}, {"type": "SWITCH ROOM HV", "qty": 1}, {"type": "TREATED GREY WATER INTERMEDIATE PUMP SET", "qty": 1}, {"type": "TREATED WASTE WATER INTERMEDIATE TANK", "qty": 1}, {"type": "TX", "qty": 2}, {"type": "WET RISER DUTY PUMP -STAGE 2", "qty": 1}, {"type": "WET RISER DUTY PUMP -STAGE 3", "qty": 1}, {"type": "WET RISER INTERMEDIATE TANK", "qty": 1}, {"type": "WET RISER JOCKEY PUMP -STAGE 2", "qty": 1}, {"type": "WET RISER JOCKEY PUMP -STAGE 3", "qty": 1}, {"type": "WET RISER PUMP CONTROL PANEL -STAGE 2", "qty": 1}, {"type": "WET RISER PUMP CONTROL PANEL -STAGE 3", "qty": 1}, {"type": "WET RISER STANDBY PUMP -STAGE 2", "qty": 1}, {"type": "WET RISER STANDBY PUMP -STAGE 3", "qty": 1}], "L19": [{"type": "AHU", "qty": 1}, {"type": "DB", "qty": 7}, {"type": "EL", "qty": 1}, {"type": "ELECTRONIC AIR FLITER", "qty": 1}, {"type": "EXIT SIGN", "qty": 1}, {"type": "FCU (CHW)", "qty": 4}, {"type": "FIRE EXTINGUISHER ABC", "qty": 6}, {"type": "FIRE EXTINGUISHER CO2", "qty": 3}, {"type": "FIRE RATED ROLLER SHUTTER", "qty": 4}, {"type": "FIREMAN SWITCH", "qty": 2}, {"type": "FM 200", "qty": 4}, {"type": "HAND DRYER", "qty": 2}, {"type": "LUMINARIES", "qty": 1}, {"type": "PABX", "qty": 1}, {"type": "PAC", "qty": 3}, {"type": "PANIC BUTTON", "qty": 1}, {"type": "S/S/O", "qty": 1}, {"type": "SSB", "qty": 5}, {"type": "UPS", "qty": 1}, {"type": "VAV", "qty": 6}, {"type": "VESDA", "qty": 4}, {"type": "VSD", "qty": 1}], "L20": [{"type": "AHU", "qty": 2}, {"type": "DB", "qty": 10}, {"type": "EL", "qty": 1}, {"type": "ELECTRONIC AIR FLITER", "qty": 2}, {"type": "EXIT SIGN", "qty": 1}, {"type": "FCU (CHW)", "qty": 2}, {"type": "FIRE EXTINGUISHER ABC", "qty": 6}, {"type": "FIRE EXTINGUISHER CO2", "qty": 3}, {"type": "FIREMAN SWITCH", "qty": 1}, {"type": "HAND DRYER", "qty": 2}, {"type": "LUMINARIES", "qty": 1}, {"type": "PANIC BUTTON", "qty": 1}, {"type": "S/S/O", "qty": 1}, {"type": "SSB", "qty": 5}, {"type": "VAV", "qty": 12}, {"type": "VSD", "qty": 2}], "L21": [{"type": "AHU", "qty": 2}, {"type": "DB", "qty": 10}, {"type": "EL", "qty": 1}, {"type": "ELECTRONIC AIR FLITER", "qty": 2}, {"type": "EXIT SIGN", "qty": 1}, {"type": "FCU (CHW)", "qty": 2}, {"type": "FIRE EXTINGUISHER ABC", "qty": 6}, {"type": "FIRE EXTINGUISHER CO2", "qty": 3}, {"type": "FIREMAN SWITCH", "qty": 1}, {"type": "HAND DRYER", "qty": 2}, {"type": "LUMINARIES", "qty": 1}, {"type": "PANIC BUTTON", "qty": 1}, {"type": "S/S/O", "qty": 1}, {"type": "SSB", "qty": 5}, {"type": "VAV", "qty": 12}, {"type": "VSD", "qty": 2}], "L22": [{"type": "AHU", "qty": 2}, {"type": "DB", "qty": 10}, {"type": "EL", "qty": 1}, {"type": "ELECTRONIC AIR FLITER", "qty": 2}, {"type": "EXIT SIGN", "qty": 1}, {"type": "FCU (CHW)", "qty": 2}, {"type": "FIRE EXTINGUISHER ABC", "qty": 6}, {"type": "FIRE EXTINGUISHER CO2", "qty": 3}, {"type": "FIREMAN SWITCH", "qty": 1}, {"type": "HAND DRYER", "qty": 2}, {"type": "LUMINARIES", "qty": 1}, {"type": "PANIC BUTTON", "qty": 1}, {"type": "S/S/O", "qty": 1}, {"type": "SSB", "qty": 5}, {"type": "VAV", "qty": 12}, {"type": "VSD", "qty": 2}], "L23": [{"type": "AHU", "qty": 2}, {"type": "DB", "qty": 10}, {"type": "EL", "qty": 1}, {"type": "ELECTRONIC AIR FLITER", "qty": 2}, {"type": "EXIT SIGN", "qty": 1}, {"type": "FCU (CHW)", "qty": 2}, {"type": "FIRE EXTINGUISHER ABC", "qty": 6}, {"type": "FIRE EXTINGUISHER CO2", "qty": 3}, {"type": "FIREMAN SWITCH", "qty": 1}, {"type": "HAND DRYER", "qty": 2}, {"type": "LUMINARIES", "qty": 1}, {"type": "PANIC BUTTON", "qty": 1}, {"type": "S/S/O", "qty": 1}, {"type": "SSB", "qty": 5}, {"type": "VAV", "qty": 12}, {"type": "VSD", "qty": 2}], "L24": [{"type": "AHU", "qty": 2}, {"type": "DB", "qty": 10}, {"type": "EL", "qty": 1}, {"type": "ELECTRONIC AIR FLITER", "qty": 2}, {"type": "EXIT SIGN", "qty": 1}, {"type": "FCU (CHW)", "qty": 2}, {"type": "FIRE EXTINGUISHER ABC", "qty": 6}, {"type": "FIRE EXTINGUISHER CO2", "qty": 3}, {"type": "FIREMAN SWITCH", "qty": 1}, {"type": "HAND DRYER", "qty": 2}, {"type": "LUMINARIES", "qty": 1}, {"type": "PANIC BUTTON", "qty": 1}, {"type": "S/S/O", "qty": 1}, {"type": "SSB", "qty": 5}, {"type": "VAV", "qty": 10}, {"type": "VSD", "qty": 2}], "L25": [{"type": "AHU", "qty": 2}, {"type": "DB", "qty": 10}, {"type": "EL", "qty": 1}, {"type": "ELECTRONIC AIR FLITER", "qty": 2}, {"type": "EXIT SIGN", "qty": 1}, {"type": "FCU (CHW)", "qty": 2}, {"type": "FIRE EXTINGUISHER ABC", "qty": 6}, {"type": "FIRE EXTINGUISHER CO2", "qty": 3}, {"type": "FIREMAN SWITCH", "qty": 1}, {"type": "HAND DRYER", "qty": 2}, {"type": "LUMINARIES", "qty": 1}, {"type": "PANIC BUTTON", "qty": 1}, {"type": "S/S/O", "qty": 1}, {"type": "SSB", "qty": 5}, {"type": "VAV", "qty": 10}, {"type": "VSD", "qty": 2}], "L26": [{"type": "AHU", "qty": 2}, {"type": "DB", "qty": 10}, {"type": "EL", "qty": 1}, {"type": "ELECTRONIC AIR FLITER", "qty": 2}, {"type": "EXIT SIGN", "qty": 1}, {"type": "FCU (CHW)", "qty": 2}, {"type": "FIRE EXTINGUISHER ABC", "qty": 6}, {"type": "FIRE EXTINGUISHER CO2", "qty": 3}, {"type": "FIREMAN SWITCH", "qty": 1}, {"type": "HAND DRYER", "qty": 2}, {"type": "LUMINARIES", "qty": 1}, {"type": "PANIC BUTTON", "qty": 1}, {"type": "S/S/O", "qty": 1}, {"type": "SSB", "qty": 5}, {"type": "VAV", "qty": 10}, {"type": "VSD", "qty": 2}], "L27": [{"type": "AHU", "qty": 2}, {"type": "DB", "qty": 10}, {"type": "EL", "qty": 1}, {"type": "ELECTRONIC AIR FLITER", "qty": 2}, {"type": "EXIT SIGN", "qty": 1}, {"type": "FCU (CHW)", "qty": 2}, {"type": "FIRE EXTINGUISHER ABC", "qty": 6}, {"type": "FIRE EXTINGUISHER CO2", "qty": 3}, {"type": "FIREMAN SWITCH", "qty": 1}, {"type": "HAND DRYER", "qty": 2}, {"type": "LUMINARIES", "qty": 1}, {"type": "PANIC BUTTON", "qty": 1}, {"type": "S/S/O", "qty": 1}, {"type": "SSB", "qty": 5}, {"type": "VAV", "qty": 10}, {"type": "VSD", "qty": 2}], "L28": [{"type": "AHU", "qty": 2}, {"type": "DB", "qty": 10}, {"type": "EL", "qty": 1}, {"type": "ELECTRONIC AIR FLITER", "qty": 2}, {"type": "EXIT SIGN", "qty": 1}, {"type": "FCU (CHW)", "qty": 2}, {"type": "FIRE EXTINGUISHER ABC", "qty": 6}, {"type": "FIRE EXTINGUISHER CO2", "qty": 3}, {"type": "FIREMAN SWITCH", "qty": 1}, {"type": "HAND DRYER", "qty": 2}, {"type": "LUMINARIES", "qty": 1}, {"type": "PANIC BUTTON", "qty": 1}, {"type": "S/S/O", "qty": 1}, {"type": "SSB", "qty": 5}, {"type": "VAV", "qty": 10}, {"type": "VSD", "qty": 2}], "L29": [{"type": "AHU", "qty": 2}, {"type": "DB", "qty": 10}, {"type": "EL", "qty": 1}, {"type": "ELECTRONIC AIR FLITER", "qty": 2}, {"type": "EXIT SIGN", "qty": 1}, {"type": "FCU (CHW)", "qty": 2}, {"type": "FIRE EXTINGUISHER ABC", "qty": 6}, {"type": "FIRE EXTINGUISHER CO2", "qty": 3}, {"type": "FIREMAN SWITCH", "qty": 1}, {"type": "HAND DRYER", "qty": 2}, {"type": "LUMINARIES", "qty": 1}, {"type": "PANIC BUTTON", "qty": 1}, {"type": "S/S/O", "qty": 1}, {"type": "SSB", "qty": 5}, {"type": "VAV", "qty": 10}, {"type": "VSD", "qty": 2}], "L30": [{"type": "AHU", "qty": 2}, {"type": "DB", "qty": 10}, {"type": "EL", "qty": 1}, {"type": "ELECTRONIC AIR FLITER", "qty": 2}, {"type": "EXIT SIGN", "qty": 1}, {"type": "FCU (CHW)", "qty": 2}, {"type": "FIRE EXTINGUISHER ABC", "qty": 6}, {"type": "FIRE EXTINGUISHER CO2", "qty": 3}, {"type": "FIREMAN SWITCH", "qty": 1}, {"type": "HAND DRYER", "qty": 2}, {"type": "LUMINARIES", "qty": 1}, {"type": "PANIC BUTTON", "qty": 1}, {"type": "S/S/O", "qty": 1}, {"type": "SSB", "qty": 5}, {"type": "VAV", "qty": 10}, {"type": "VSD", "qty": 2}], "L31": [{"type": "AHU", "qty": 2}, {"type": "DB", "qty": 10}, {"type": "EL", "qty": 1}, {"type": "ELECTRONIC AIR FLITER", "qty": 2}, {"type": "EXIT SIGN", "qty": 1}, {"type": "FCU (CHW)", "qty": 2}, {"type": "FIRE EXTINGUISHER ABC", "qty": 6}, {"type": "FIRE EXTINGUISHER CO2", "qty": 3}, {"type": "FIREMAN SWITCH", "qty": 1}, {"type": "HAND DRYER", "qty": 2}, {"type": "LUMINARIES", "qty": 1}, {"type": "PANIC BUTTON", "qty": 1}, {"type": "S/S/O", "qty": 1}, {"type": "SSB", "qty": 5}, {"type": "VAV", "qty": 10}, {"type": "VSD", "qty": 2}], "L32": [{"type": "AHU", "qty": 2}, {"type": "DB", "qty": 10}, {"type": "EL", "qty": 1}, {"type": "ELECTRONIC AIR FLITER", "qty": 2}, {"type": "EXIT SIGN", "qty": 1}, {"type": "FCU (CHW)", "qty": 3}, {"type": "FIRE EXTINGUISHER ABC", "qty": 6}, {"type": "FIRE EXTINGUISHER CO2", "qty": 3}, {"type": "FIREMAN SWITCH", "qty": 1}, {"type": "HAND DRYER", "qty": 2}, {"type": "LUMINARIES", "qty": 1}, {"type": "OUTDOOR LIGHTING", "qty": 1}, {"type": "PANIC BUTTON", "qty": 1}, {"type": "S/S/O", "qty": 1}, {"type": "SSB", "qty": 5}, {"type": "VAV", "qty": 10}, {"type": "VSD", "qty": 2}], "L33": [{"type": "AHU", "qty": 2}, {"type": "DB", "qty": 10}, {"type": "EL", "qty": 1}, {"type": "ELECTRONIC AIR FLITER", "qty": 2}, {"type": "EXHAUST FAN", "qty": 1}, {"type": "EXIT SIGN", "qty": 1}, {"type": "FCU (CHW)", "qty": 3}, {"type": "FIRE EXTINGUISHER ABC", "qty": 5}, {"type": "FIRE EXTINGUISHER CO2", "qty": 3}, {"type": "FIREMAN SWITCH", "qty": 1}, {"type": "HAND DRYER", "qty": 2}, {"type": "INSTANT WATER HEATER", "qty": 1}, {"type": "LUMINARIES", "qty": 1}, {"type": "OUTDOOR LIGHTING", "qty": 1}, {"type": "PANIC BUTTON", "qty": 1}, {"type": "S/S/O", "qty": 1}, {"type": "SSB", "qty": 5}, {"type": "VAV", "qty": 8}, {"type": "VISUAL PROJECTION", "qty": 1}, {"type": "VSD", "qty": 2}], "L34": [{"type": "AHU", "qty": 2}, {"type": "DB", "qty": 10}, {"type": "EL", "qty": 1}, {"type": "ELECTRONIC AIR FLITER", "qty": 2}, {"type": "EXIT SIGN", "qty": 1}, {"type": "FCU (CHW)", "qty": 3}, {"type": "FIRE EXTINGUISHER ABC", "qty": 5}, {"type": "FIRE EXTINGUISHER CO2", "qty": 3}, {"type": "FIREMAN SWITCH", "qty": 1}, {"type": "HAND DRYER", "qty": 2}, {"type": "INSTANT WATER HEATER", "qty": 2}, {"type": "LUMINARIES", "qty": 1}, {"type": "OUTDOOR LIGHTING", "qty": 1}, {"type": "PANIC BUTTON", "qty": 1}, {"type": "S/S/O", "qty": 1}, {"type": "SSB", "qty": 5}, {"type": "VAV", "qty": 8}, {"type": "VISUAL PROJECTION", "qty": 1}, {"type": "VSD", "qty": 2}], "L35": [{"type": "AHU", "qty": 2}, {"type": "CONFERENCE SYSTEM", "qty": 1}, {"type": "DB", "qty": 10}, {"type": "EL", "qty": 1}, {"type": "ELECTRONIC AIR FLITER", "qty": 2}, {"type": "EXIT SIGN", "qty": 1}, {"type": "FCU (CHW)", "qty": 3}, {"type": "FIRE EXTINGUISHER ABC", "qty": 5}, {"type": "FIRE EXTINGUISHER CO2", "qty": 3}, {"type": "FIREMAN SWITCH", "qty": 1}, {"type": "HAND DRYER", "qty": 2}, {"type": "INSTANT WATER HEATER", "qty": 1}, {"type": "LUMINARIES", "qty": 1}, {"type": "OUTDOOR LIGHTING", "qty": 2}, {"type": "PANIC BUTTON", "qty": 1}, {"type": "S/S/O", "qty": 1}, {"type": "SOUND REINFORCEMENT SYSTEM", "qty": 1}, {"type": "SSB", "qty": 5}, {"type": "VAV", "qty": 6}, {"type": "VISUAL PROJECTION", "qty": 1}, {"type": "VSD", "qty": 2}], "L36": [{"type": "ACSU", "qty": 5}, {"type": "AIR COOLED CHILLER", "qty": 2}, {"type": "CHWP", "qty": 2}, {"type": "DB", "qty": 4}, {"type": "DCW STORAGE TANK 1(BASIN)", "qty": 1}, {"type": "DCW STORAGE TANK 2(WC&URINAL)", "qty": 1}, {"type": "DOMESTIC COLD WATER BOOSTER PUMP(WASH BASIN)", "qty": 1}, {"type": "DOMESTIC COLD WATER BOOSTER PUMP(WC FLUSH VALVE)", "qty": 1}, {"type": "EL", "qty": 1}, {"type": "EXHAUST FAN", "qty": 1}, {"type": "EXIT SIGN", "qty": 1}, {"type": "FIRE EXTINGUISHER ABC", "qty": 5}, {"type": "FIRE EXTINGUISHER CO2", "qty": 4}, {"type": "FIREMAN SWITCH", "qty": 1}, {"type": "FRESH AIR FAN", "qty": 1}, {"type": "GONDOLA", "qty": 1}, {"type": "HEAT RECOVERY WHEEL", "qty": 1}, {"type": "HOSE REEL DUTY PUMP", "qty": 1}, {"type": "HOSE REEL PUMP CONTROL PANEL", "qty": 1}, {"type": "HOSE REEL STANDBY PUMP", "qty": 1}, {"type": "HOSE REEL WATER TANK STORAGE", "qty": 1}, {"type": "LUMINARIES", "qty": 1}, {"type": "OUTDOOR LIGHTING", "qty": 1}, {"type": "RAIN WATER HARVESTING TANK", "qty": 1}, {"type": "S/S/O", "qty": 1}, {"type": "SECONDARY CHILLED WATER EXPANSION TANK", "qty": 1}, {"type": "SMOKE SPILL FAN", "qty": 2}, {"type": "SSB", "qty": 11}, {"type": "TREATED WASTE WATER ROOF STORAGE TANK (WC&URINAL)", "qty": 1}], "L37": [{"type": "FIRE EXTINGUISHER ABC", "qty": 1}, {"type": "FIRE EXTINGUISHER CO2", "qty": 1}, {"type": "LIFT-FL1", "qty": 1}, {"type": "LIFT-PL01 HIGHZONE", "qty": 1}, {"type": "LIFT-PL02 HIGHZONE", "qty": 1}, {"type": "LIFT-PL03 HIGHZONE", "qty": 1}, {"type": "LIFT-PL04 HIGHZONE", "qty": 1}, {"type": "LIFT-PL05 HIGHZONE", "qty": 1}, {"type": "LIFT-PL06 HIGHZONE", "qty": 1}, {"type": "SMATV", "qty": 1}]}